ea2drawio/__init__.py
ea2drawio/cli.py
ea2drawio/eadefault.json
ea2drawio-0.2.2.dist-info/licenses/LICENSE
ea2drawio-0.2.2.dist-info/METADATA
ea2drawio-0.2.2.dist-info/WHEEL
ea2drawio-0.2.2.dist-info/entry_points.txt
ea2drawio-0.2.2.dist-info/top_level.txt
ea2drawio-0.2.2.dist-info/RECORD
