Metadata-Version: 2.4
Name: ea2drawio
Version: 0.2.2
Summary: Convert EA diagrams to draw.io format
Author-email: Andrey Kolesov <never-ya@yandex.ru>
License-Expression: MIT
Classifier: Programming Language :: Python :: 3
Classifier: Operating System :: Microsoft :: Windows
Requires-Python: >=3.7
License-File: LICENSE
Requires-Dist: pywin32
Dynamic: license-file
